{
  "lastUpdated": "2026-03-28T10:36:53.281Z",
  "lastUpdatedReadable": "3/28/2026, 4:21:53 PM",
  "statistics": {
    "totalKeys": 1,
    "activeKeys": 1,
    "expiredKeys": 0,
    "bannedKeys": 0,
    "activeSessions": 0
  },
  "keys": {
    "DEVIL-797B-1B50-7658-D944": {
      "discordId": "931823254195294228",
      "ip": "103.190.41.251",
      "createdAt": "2026-03-28T10:20:31.152Z",
      "expiresAt": "2026-03-30T22:20:31.153Z",
      "extensionCount": 1,
      "lastExtensionDate": "2026-03-28",
      "banned": false,
      "status": "ACTIVE"
    }
  },
  "sessions": {}
}